flet_fonts/__init__.py
flet_fonts/flet_fonts.py
flet_fonts/font_data.py
flet_fonts/text_span.py
flet_fonts-0.1.6.dist-info/licenses/LICENSE
flutter/flet_fonts/CHANGELOG.md
flutter/flet_fonts/LICENSE
flutter/flet_fonts/README.md
flutter/flet_fonts/pubspec.lock
flutter/flet_fonts/pubspec.yaml
flutter/flet_fonts/lib/flet_fonts.dart
flutter/flet_fonts/lib/src/extension.dart
flutter/flet_fonts/lib/src/flet_fonts.dart
flutter/flet_fonts/lib/src/utils/google_fonts.dart
flutter/flet_fonts/lib/src/utils/text_span.dart
flet_fonts-0.1.6.dist-info/METADATA
flet_fonts-0.1.6.dist-info/WHEEL
flet_fonts-0.1.6.dist-info/top_level.txt
flet_fonts-0.1.6.dist-info/RECORD
