Metadata-Version: 2.4
Name: flet-fonts
Version: 0.1.6
Summary: flet-fonts uses the Google Fonts library in the background
Author-email: Arief Minardi <ariefminardi005@gmail.com>
Project-URL: Repository, https://github.com/arief05652/flet-fonts
Project-URL: Issues, https://github.com/arief05652/flet-fonts/issues
Requires-Python: >=3.12
License-File: LICENSE
Requires-Dist: flet>=0.80.0
Dynamic: license-file
